ComposeNomadConvertor-0.0.4.data/scripts/nomadgen
composenomadconvertor/__init__.py
composenomadconvertor/__main__.py
composenomadconvertor/arg_parser.py
composenomadconvertor/compose_defaults.py
composenomadconvertor/folder_compressor.py
composenomadconvertor/produce_tasks.py
ComposeNomadConvertor-0.0.4.dist-info/METADATA
ComposeNomadConvertor-0.0.4.dist-info/WHEEL
ComposeNomadConvertor-0.0.4.dist-info/top_level.txt
ComposeNomadConvertor-0.0.4.dist-info/RECORD
