Metadata-Version: 2.1
Name: ComposeNomadConvertor
Version: 0.0.4
Summary: Docker Compose to Nomad job convertor
Home-page: UNKNOWN
Author: Uchenic
Author-email: uchenic@protonmail.com
License: UNKNOWN
Platform: UNKNOWN
Requires-Dist: pyyaml
Requires-Dist: ComposeParser
